pyramid_unicodedammit/__init__.py
pyramid_unicodedammit/tests.py
pyramid_unicodedammit-0.0.1.dist-info/DESCRIPTION.rst
pyramid_unicodedammit-0.0.1.dist-info/METADATA
pyramid_unicodedammit-0.0.1.dist-info/RECORD
pyramid_unicodedammit-0.0.1.dist-info/WHEEL
pyramid_unicodedammit-0.0.1.dist-info/metadata.json
pyramid_unicodedammit-0.0.1.dist-info/top_level.txt
pyramid_unicodedammit-0.0.1.dist-info/zip-safe
